nednl/__init__.py
nednl/exceptions.py
nednl/models.py
nednl/nednl.py
nednl/py.typed
nednl-0.2.0.dist-info/LICENSE
nednl-0.2.0.dist-info/METADATA
nednl-0.2.0.dist-info/WHEEL
nednl-0.2.0.dist-info/RECORD
