Metadata-Version: 2.3
Name: nednl
Version: 0.2.0
Summary: Gain insight into current and predictive energy data from The Netherlands
License: MIT
Keywords: nednl,api,async,client,ned,energy
Author: Klaas Schoute
Author-email: <hello@student-techlife.com>
Maintainer: Klaas Schoute
Maintainer-email: <hello@student-techlife.com>
Requires-Python: >=3.11
Classifier: Framework :: AsyncIO
Classifier: Intended Audience :: Developers
Classifier: License :: OSI Approved :: MIT License
Classifier: Natural Language :: English
Classifier: Programming Language :: Python :: 3.11
Classifier: Programming Language :: Python :: 3.12
Classifier: Programming Language :: Python :: 3.13
Classifier: Programming Language :: Python :: 3
Classifier: Topic :: Software Development :: Libraries :: Python Modules
Requires-Dist: aiohttp (>=3.0.0)
Requires-Dist: mashumaro (>=3.12,<4.0)
Requires-Dist: orjson (>=3.9.15,<4.0.0)
Requires-Dist: yarl (>=1.6.0)
Project-URL: Bug Tracker, https://github.com/klaasnicolaas/python-nednl/issues
Project-URL: Changelog, https://github.com/klaasnicolaas/python-nednl/releases
Project-URL: Documentation, https://github.com/klaasnicolaas/python-nednl
Project-URL: Homepage, https://github.com/klaasnicolaas/python-nednl
Project-URL: Repository, https://github.com/klaasnicolaas/python-nednl
